[
  {
    "name": "wd",
    "value": "780x493",
    "domain": ".instagram.com",
    "path": "/",
    "expires": 1750965208,
    "size": 9,
    "httpOnly": false,
    "secure": true,
    "session": false,
    "sameSite": "Lax",
    "priority": "Medium",
    "sameParty": false,
    "sourceScheme": "Secure"
  },
  {
    "name": "ps_n",
    "value": "1",
    "domain": ".instagram.com",
    "path": "/",
    "expires": 1784920407.185465,
    "size": 5,
    "httpOnly": true,
    "secure": true,
    "session": false,
    "sameSite": "None",
    "priority": "Medium",
    "sameParty": false,
    "sourceScheme": "Secure"
  },
  {
    "name": "ps_l",
    "value": "1",
    "domain": ".instagram.com",
    "path": "/",
    "expires": 1784920407.185308,
    "size": 5,
    "httpOnly": true,
    "secure": true,
    "session": false,
    "sameSite": "Lax",
    "priority": "Medium",
    "sameParty": false,
    "sourceScheme": "Secure"
  },
  {
    "name": "mid",
    "value": "aFRhVgAEAAGrfTdB703ewOx_LqEY",
    "domain": ".instagram.com",
    "path": "/",
    "expires": 1784920408,
    "size": 31,
    "httpOnly": false,
    "secure": true,
    "session": false,
    "priority": "Medium",
    "sameParty": false,
    "sourceScheme": "Secure"
  },
  {
    "name": "ig_did",
    "value": "A00E5F43-2D19-47CC-9243-6BBB8264CF59",
    "domain": ".instagram.com",
    "path": "/",
    "expires": 1781896418.620478,
    "size": 42,
    "httpOnly": true,
    "secure": true,
    "session": false,
    "priority": "Medium",
    "sameParty": false,
    "sourceScheme": "Secure"
  },
  {
    "name": "ig_nrcb",
    "value": "1",
    "domain": ".instagram.com",
    "path": "/",
    "expires": 1781896408.000388,
    "size": 8,
    "httpOnly": false,
    "secure": true,
    "session": false,
    "priority": "Medium",
    "sameParty": false,
    "sourceScheme": "Secure"
  },
  {
    "name": "datr",
    "value": "VmFUaCKvM--vC6Mxxam7KhEg",
    "domain": ".instagram.com",
    "path": "/",
    "expires": 1784920406.953171,
    "size": 28,
    "httpOnly": true,
    "secure": true,
    "session": false,
    "sameSite": "None",
    "priority": "Medium",
    "sameParty": false,
    "sourceScheme": "Secure"
  },
  {
    "name": "csrftoken",
    "value": "sC2nM6E_eMOYcz3Tz30qB1",
    "domain": ".instagram.com",
    "path": "/",
    "expires": 1784920418.620255,
    "size": 31,
    "httpOnly": false,
    "secure": true,
    "session": false,
    "priority": "Medium",
    "sameParty": false,
    "sourceScheme": "Secure"
  }
]