[
  {
    "name": "ps_n",
    "value": "1",
    "domain": ".instagram.com",
    "path": "/",
    "expires": 1784921829.883795,
    "size": 5,
    "httpOnly": true,
    "secure": true,
    "session": false,
    "sameSite": "None",
    "priority": "Medium",
    "sameParty": false,
    "sourceScheme": "Secure"
  },
  {
    "name": "ps_l",
    "value": "1",
    "domain": ".instagram.com",
    "path": "/",
    "expires": 1784921829.883654,
    "size": 5,
    "httpOnly": true,
    "secure": true,
    "session": false,
    "sameSite": "Lax",
    "priority": "Medium",
    "sameParty": false,
    "sourceScheme": "Secure"
  },
  {
    "name": "wd",
    "value": "780x493",
    "domain": ".instagram.com",
    "path": "/",
    "expires": 1750966613,
    "size": 9,
    "httpOnly": false,
    "secure": true,
    "session": false,
    "sameSite": "Lax",
    "priority": "Medium",
    "sameParty": false,
    "sourceScheme": "Secure"
  },
  {
    "name": "mid",
    "value": "aFRm0wAEAAH6V7pP1S4QHoh1rUvc",
    "domain": ".instagram.com",
    "path": "/",
    "expires": 1784921813,
    "size": 31,
    "httpOnly": false,
    "secure": true,
    "session": false,
    "priority": "Medium",
    "sameParty": false,
    "sourceScheme": "Secure"
  },
  {
    "name": "ig_did",
    "value": "F56ADBD1-6BDE-45DA-A7E1-54E20F466441",
    "domain": ".instagram.com",
    "path": "/",
    "expires": 1781897824.65763,
    "size": 42,
    "httpOnly": true,
    "secure": true,
    "session": false,
    "priority": "Medium",
    "sameParty": false,
    "sourceScheme": "Secure"
  },
  {
    "name": "ig_nrcb",
    "value": "1",
    "domain": ".instagram.com",
    "path": "/",
    "expires": 1781897813.120245,
    "size": 8,
    "httpOnly": false,
    "secure": true,
    "session": false,
    "priority": "Medium",
    "sameParty": false,
    "sourceScheme": "Secure"
  },
  {
    "name": "datr",
    "value": "02ZUaGrFlNaKYZTFZ7D3EVBx",
    "domain": ".instagram.com",
    "path": "/",
    "expires": 1784921811.935021,
    "size": 28,
    "httpOnly": true,
    "secure": true,
    "session": false,
    "sameSite": "None",
    "priority": "Medium",
    "sameParty": false,
    "sourceScheme": "Secure"
  },
  {
    "name": "csrftoken",
    "value": "mdQxbaMu4LZ_yFLgJd6OVZ",
    "domain": ".instagram.com",
    "path": "/",
    "expires": 1784921824.657468,
    "size": 31,
    "httpOnly": false,
    "secure": true,
    "session": false,
    "priority": "Medium",
    "sameParty": false,
    "sourceScheme": "Secure"
  }
]