[
  {
    "name": "wd",
    "value": "780x493",
    "domain": ".instagram.com",
    "path": "/",
    "expires": 1750959764,
    "size": 9,
    "httpOnly": false,
    "secure": true,
    "session": false,
    "sameSite": "Lax",
    "priority": "Medium",
    "sameParty": false,
    "sourceScheme": "Secure"
  },
  {
    "name": "mid",
    "value": "aFRMEgAEAAH3coEWkZvjmtt7FsBn",
    "domain": ".instagram.com",
    "path": "/",
    "expires": 1784914964,
    "size": 31,
    "httpOnly": false,
    "secure": true,
    "session": false,
    "priority": "Medium",
    "sameParty": false,
    "sourceScheme": "Secure"
  },
  {
    "name": "ig_did",
    "value": "F127B5E6-77BB-4492-B3C8-CABD7C93609F",
    "domain": ".instagram.com",
    "path": "/",
    "expires": 1781890975.729134,
    "size": 42,
    "httpOnly": true,
    "secure": true,
    "session": false,
    "priority": "Medium",
    "sameParty": false,
    "sourceScheme": "Secure"
  },
  {
    "name": "ig_nrcb",
    "value": "1",
    "domain": ".instagram.com",
    "path": "/",
    "expires": 1781890964.044019,
    "size": 8,
    "httpOnly": false,
    "secure": true,
    "session": false,
    "priority": "Medium",
    "sameParty": false,
    "sourceScheme": "Secure"
  },
  {
    "name": "datr",
    "value": "EkxUaHgLjscpDZIkFy4ybnv6",
    "domain": ".instagram.com",
    "path": "/",
    "expires": 1784914962.60875,
    "size": 28,
    "httpOnly": true,
    "secure": true,
    "session": false,
    "sameSite": "None",
    "priority": "Medium",
    "sameParty": false,
    "sourceScheme": "Secure"
  },
  {
    "name": "csrftoken",
    "value": "fuCWloeDrE94GHQnFSkMWO",
    "domain": ".instagram.com",
    "path": "/",
    "expires": 1784914975.728969,
    "size": 31,
    "httpOnly": false,
    "secure": true,
    "session": false,
    "priority": "Medium",
    "sameParty": false,
    "sourceScheme": "Secure"
  }
]