[
  {
    "name": "wd",
    "value": "780x493",
    "domain": ".instagram.com",
    "path": "/",
    "expires": 1750927177,
    "size": 9,
    "httpOnly": false,
    "secure": true,
    "session": false,
    "sameSite": "Lax",
    "priority": "Medium",
    "sameParty": false,
    "sourceScheme": "Secure"
  },
  {
    "name": "mid",
    "value": "aFPMyAAEAAGbvOOVz7LvgG0Ww341",
    "domain": ".instagram.com",
    "path": "/",
    "expires": 1784882377,
    "size": 31,
    "httpOnly": false,
    "secure": true,
    "session": false,
    "priority": "Medium",
    "sameParty": false,
    "sourceScheme": "Secure"
  },
  {
    "name": "ig_did",
    "value": "F30D1A3B-B068-4A9F-A81B-F0918CB32AEE",
    "domain": ".instagram.com",
    "path": "/",
    "expires": 1781858387.460947,
    "size": 42,
    "httpOnly": true,
    "secure": true,
    "session": false,
    "priority": "Medium",
    "sameParty": false,
    "sourceScheme": "Secure"
  },
  {
    "name": "ig_nrcb",
    "value": "1",
    "domain": ".instagram.com",
    "path": "/",
    "expires": 1781858377.261063,
    "size": 8,
    "httpOnly": false,
    "secure": true,
    "session": false,
    "priority": "Medium",
    "sameParty": false,
    "sourceScheme": "Secure"
  },
  {
    "name": "datr",
    "value": "yMxTaKQj4KObYFMMp2Q8xAkB",
    "domain": ".instagram.com",
    "path": "/",
    "expires": 1784882376.251819,
    "size": 28,
    "httpOnly": true,
    "secure": true,
    "session": false,
    "sameSite": "None",
    "priority": "Medium",
    "sameParty": false,
    "sourceScheme": "Secure"
  },
  {
    "name": "csrftoken",
    "value": "vYCInLTo3lAKNw5snaW335",
    "domain": ".instagram.com",
    "path": "/",
    "expires": 1784882387.460825,
    "size": 31,
    "httpOnly": false,
    "secure": true,
    "session": false,
    "priority": "Medium",
    "sameParty": false,
    "sourceScheme": "Secure"
  }
]