[
  {
    "name": "wd",
    "value": "780x493",
    "domain": ".instagram.com",
    "path": "/",
    "expires": 1750967408,
    "size": 9,
    "httpOnly": false,
    "secure": true,
    "session": false,
    "sameSite": "Lax",
    "priority": "Medium",
    "sameParty": false,
    "sourceScheme": "Secure"
  },
  {
    "name": "mid",
    "value": "aFRp7gAEAAHxNOE38dB3VMuZS_5T",
    "domain": ".instagram.com",
    "path": "/",
    "expires": 1784922608,
    "size": 31,
    "httpOnly": false,
    "secure": true,
    "session": false,
    "priority": "Medium",
    "sameParty": false,
    "sourceScheme": "Secure"
  },
  {
    "name": "ig_did",
    "value": "713DA123-B8EB-4BD3-B990-2B17A8E6ED42",
    "domain": ".instagram.com",
    "path": "/",
    "expires": 1781898619.45808,
    "size": 42,
    "httpOnly": true,
    "secure": true,
    "session": false,
    "priority": "Medium",
    "sameParty": false,
    "sourceScheme": "Secure"
  },
  {
    "name": "ig_nrcb",
    "value": "1",
    "domain": ".instagram.com",
    "path": "/",
    "expires": 1781898608.113233,
    "size": 8,
    "httpOnly": false,
    "secure": true,
    "session": false,
    "priority": "Medium",
    "sameParty": false,
    "sourceScheme": "Secure"
  },
  {
    "name": "datr",
    "value": "7mlUaAXd6Mp5wMbQt75B34tc",
    "domain": ".instagram.com",
    "path": "/",
    "expires": 1784922606.905744,
    "size": 28,
    "httpOnly": true,
    "secure": true,
    "session": false,
    "sameSite": "None",
    "priority": "Medium",
    "sameParty": false,
    "sourceScheme": "Secure"
  },
  {
    "name": "csrftoken",
    "value": "BDoYrk9XQGACOmsp2-OAaR",
    "domain": ".instagram.com",
    "path": "/",
    "expires": 1784922619.457898,
    "size": 31,
    "httpOnly": false,
    "secure": true,
    "session": false,
    "priority": "Medium",
    "sameParty": false,
    "sourceScheme": "Secure"
  }
]